{
  "openapi": "3.0.1",
  "info": {
    "title": "ProductTask",
    "version": "1.0"
  },
  "paths": {
    "/api/Auth/signup": {
      "post": {
        "tags": [
          "Auth"
        ],
        "requestBody": {
          "content": {
            "application/json": {
              "schema": {
                "$ref": "#/components/schemas/UserSignUp"
              }
            },
            "text/json": {
              "schema": {
                "$ref": "#/components/schemas/UserSignUp"
              }
            },
            "application/*+json": {
              "schema": {
                "$ref": "#/components/schemas/UserSignUp"
              }
            }
          }
        },
        "responses": {
          "200": {
            "description": "OK"
          }
        }
      }
    },
    "/api/Auth/login": {
      "post": {
        "tags": [
          "Auth"
        ],
        "requestBody": {
          "content": {
            "application/json": {
              "schema": {
                "$ref": "#/components/schemas/UserLogin"
              }
            },
            "text/json": {
              "schema": {
                "$ref": "#/components/schemas/UserLogin"
              }
            },
            "application/*+json": {
              "schema": {
                "$ref": "#/components/schemas/UserLogin"
              }
            }
          }
        },
        "responses": {
          "200": {
            "description": "OK"
          }
        }
      }
    },
    "/api/Auth/RefreshToken": {
      "get": {
        "tags": [
          "Auth"
        ],
        "responses": {
          "200": {
            "description": "OK"
          }
        }
      }
    },
    "/api/Auth/change-password": {
      "post": {
        "tags": [
          "Auth"
        ],
        "requestBody": {
          "content": {
            "application/json": {
              "schema": {
                "$ref": "#/components/schemas/ChangePasswordDto"
              }
            },
            "text/json": {
              "schema": {
                "$ref": "#/components/schemas/ChangePasswordDto"
              }
            },
            "application/*+json": {
              "schema": {
                "$ref": "#/components/schemas/ChangePasswordDto"
              }
            }
          }
        },
        "responses": {
          "200": {
            "description": "OK"
          }
        }
      }
    },
    "/api/CheckoutForm": {
      "get": {
        "tags": [
          "CheckoutForm"
        ],
        "responses": {
          "200": {
            "description": "OK",
            "content": {
              "text/plain": {
                "schema": {
                  "type": "array",
                  "items": {
                    "$ref": "#/components/schemas/CheckoutForm"
                  }
                }
              },
              "application/json": {
                "schema": {
                  "type": "array",
                  "items": {
                    "$ref": "#/components/schemas/CheckoutForm"
                  }
                }
              },
              "text/json": {
                "schema": {
                  "type": "array",
                  "items": {
                    "$ref": "#/components/schemas/CheckoutForm"
                  }
                }
              }
            }
          }
        }
      },
      "post": {
        "tags": [
          "CheckoutForm"
        ],
        "requestBody": {
          "content": {
            "application/json": {
              "schema": {
                "$ref": "#/components/schemas/CheckoutForm"
              }
            },
            "text/json": {
              "schema": {
                "$ref": "#/components/schemas/CheckoutForm"
              }
            },
            "application/*+json": {
              "schema": {
                "$ref": "#/components/schemas/CheckoutForm"
              }
            }
          }
        },
        "responses": {
          "200": {
            "description": "OK"
          }
        }
      }
    },
    "/api/CheckoutForm/{id}": {
      "get": {
        "tags": [
          "CheckoutForm"
        ],
        "parameters": [
          {
            "name": "id",
            "in": "path",
            "required": true,
            "schema": {
              "type": "integer",
              "format": "int32"
            }
          }
        ],
        "responses": {
          "200": {
            "description": "OK",
            "content": {
              "text/plain": {
                "schema": {
                  "$ref": "#/components/schemas/CheckoutForm"
                }
              },
              "application/json": {
                "schema": {
                  "$ref": "#/components/schemas/CheckoutForm"
                }
              },
              "text/json": {
                "schema": {
                  "$ref": "#/components/schemas/CheckoutForm"
                }
              }
            }
          }
        }
      },
      "put": {
        "tags": [
          "CheckoutForm"
        ],
        "parameters": [
          {
            "name": "id",
            "in": "path",
            "required": true,
            "schema": {
              "type": "integer",
              "format": "int32"
            }
          }
        ],
        "requestBody": {
          "content": {
            "application/json": {
              "schema": {
                "$ref": "#/components/schemas/CheckoutForm"
              }
            },
            "text/json": {
              "schema": {
                "$ref": "#/components/schemas/CheckoutForm"
              }
            },
            "application/*+json": {
              "schema": {
                "$ref": "#/components/schemas/CheckoutForm"
              }
            }
          }
        },
        "responses": {
          "200": {
            "description": "OK"
          }
        }
      },
      "delete": {
        "tags": [
          "CheckoutForm"
        ],
        "parameters": [
          {
            "name": "id",
            "in": "path",
            "required": true,
            "schema": {
              "type": "integer",
              "format": "int32"
            }
          }
        ],
        "responses": {
          "200": {
            "description": "OK"
          }
        }
      }
    },
    "/api/CheckoutForm/managed": {
      "get": {
        "tags": [
          "CheckoutForm"
        ],
        "responses": {
          "200": {
            "description": "OK",
            "content": {
              "text/plain": {
                "schema": {
                  "type": "array",
                  "items": {
                    "$ref": "#/components/schemas/ViewOrder"
                  }
                }
              },
              "application/json": {
                "schema": {
                  "type": "array",
                  "items": {
                    "$ref": "#/components/schemas/ViewOrder"
                  }
                }
              },
              "text/json": {
                "schema": {
                  "type": "array",
                  "items": {
                    "$ref": "#/components/schemas/ViewOrder"
                  }
                }
              }
            }
          }
        }
      }
    },
    "/api/Orders": {
      "get": {
        "tags": [
          "Orders"
        ],
        "responses": {
          "200": {
            "description": "OK",
            "content": {
              "text/plain": {
                "schema": {
                  "type": "array",
                  "items": {
                    "$ref": "#/components/schemas/OrderDto"
                  }
                }
              },
              "application/json": {
                "schema": {
                  "type": "array",
                  "items": {
                    "$ref": "#/components/schemas/OrderDto"
                  }
                }
              },
              "text/json": {
                "schema": {
                  "type": "array",
                  "items": {
                    "$ref": "#/components/schemas/OrderDto"
                  }
                }
              }
            }
          }
        }
      },
      "post": {
        "tags": [
          "Orders"
        ],
        "requestBody": {
          "content": {
            "application/json": {
              "schema": {
                "$ref": "#/components/schemas/OrderDto"
              }
            },
            "text/json": {
              "schema": {
                "$ref": "#/components/schemas/OrderDto"
              }
            },
            "application/*+json": {
              "schema": {
                "$ref": "#/components/schemas/OrderDto"
              }
            }
          }
        },
        "responses": {
          "200": {
            "description": "OK"
          }
        }
      }
    },
    "/api/Orders/{id}": {
      "get": {
        "tags": [
          "Orders"
        ],
        "parameters": [
          {
            "name": "id",
            "in": "path",
            "required": true,
            "schema": {
              "type": "integer",
              "format": "int32"
            }
          }
        ],
        "responses": {
          "200": {
            "description": "OK",
            "content": {
              "text/plain": {
                "schema": {
                  "$ref": "#/components/schemas/OrderDto"
                }
              },
              "application/json": {
                "schema": {
                  "$ref": "#/components/schemas/OrderDto"
                }
              },
              "text/json": {
                "schema": {
                  "$ref": "#/components/schemas/OrderDto"
                }
              }
            }
          }
        }
      },
      "put": {
        "tags": [
          "Orders"
        ],
        "parameters": [
          {
            "name": "id",
            "in": "path",
            "required": true,
            "schema": {
              "type": "integer",
              "format": "int32"
            }
          }
        ],
        "requestBody": {
          "content": {
            "application/json": {
              "schema": {
                "$ref": "#/components/schemas/OrderDto"
              }
            },
            "text/json": {
              "schema": {
                "$ref": "#/components/schemas/OrderDto"
              }
            },
            "application/*+json": {
              "schema": {
                "$ref": "#/components/schemas/OrderDto"
              }
            }
          }
        },
        "responses": {
          "200": {
            "description": "OK"
          }
        }
      },
      "delete": {
        "tags": [
          "Orders"
        ],
        "parameters": [
          {
            "name": "id",
            "in": "path",
            "required": true,
            "schema": {
              "type": "integer",
              "format": "int32"
            }
          }
        ],
        "responses": {
          "200": {
            "description": "OK"
          }
        }
      }
    },
    "/api/Product/GetProducts": {
      "get": {
        "tags": [
          "Product"
        ],
        "responses": {
          "200": {
            "description": "OK",
            "content": {
              "text/plain": {
                "schema": {
                  "type": "array",
                  "items": {
                    "$ref": "#/components/schemas/ProductBr"
                  }
                }
              },
              "application/json": {
                "schema": {
                  "type": "array",
                  "items": {
                    "$ref": "#/components/schemas/ProductBr"
                  }
                }
              },
              "text/json": {
                "schema": {
                  "type": "array",
                  "items": {
                    "$ref": "#/components/schemas/ProductBr"
                  }
                }
              }
            }
          }
        }
      }
    },
    "/api/Product/{id}": {
      "get": {
        "tags": [
          "Product"
        ],
        "parameters": [
          {
            "name": "id",
            "in": "path",
            "required": true,
            "schema": {
              "type": "integer",
              "format": "int32"
            }
          }
        ],
        "responses": {
          "200": {
            "description": "OK",
            "content": {
              "text/plain": {
                "schema": {
                  "$ref": "#/components/schemas/ProductDto"
                }
              },
              "application/json": {
                "schema": {
                  "$ref": "#/components/schemas/ProductDto"
                }
              },
              "text/json": {
                "schema": {
                  "$ref": "#/components/schemas/ProductDto"
                }
              }
            }
          }
        }
      },
      "put": {
        "tags": [
          "Product"
        ],
        "parameters": [
          {
            "name": "id",
            "in": "path",
            "required": true,
            "schema": {
              "type": "integer",
              "format": "int32"
            }
          }
        ],
        "requestBody": {
          "content": {
            "multipart/form-data": {
              "schema": {
                "type": "object",
                "properties": {
                  "Name": {
                    "type": "string"
                  },
                  "price": {
                    "type": "number",
                    "format": "double"
                  },
                  "Description": {
                    "type": "string"
                  },
                  "ImageURL": {
                    "type": "string",
                    "format": "binary"
                  },
                  "CategoryId": {
                    "type": "integer",
                    "format": "int32"
                  },
                  "CategoryName": {
                    "type": "string"
                  }
                }
              },
              "encoding": {
                "Name": {
                  "style": "form"
                },
                "price": {
                  "style": "form"
                },
                "Description": {
                  "style": "form"
                },
                "ImageURL": {
                  "style": "form"
                },
                "CategoryId": {
                  "style": "form"
                },
                "CategoryName": {
                  "style": "form"
                }
              }
            }
          }
        },
        "responses": {
          "200": {
            "description": "OK"
          }
        }
      }
    },
    "/api/Product/productById/{id}": {
      "get": {
        "tags": [
          "Product"
        ],
        "parameters": [
          {
            "name": "id",
            "in": "path",
            "required": true,
            "schema": {
              "type": "integer",
              "format": "int32"
            }
          }
        ],
        "responses": {
          "200": {
            "description": "OK",
            "content": {
              "text/plain": {
                "schema": {
                  "$ref": "#/components/schemas/ProductBr"
                }
              },
              "application/json": {
                "schema": {
                  "$ref": "#/components/schemas/ProductBr"
                }
              },
              "text/json": {
                "schema": {
                  "$ref": "#/components/schemas/ProductBr"
                }
              }
            }
          }
        }
      }
    },
    "/api/Product/productByCategoryId/{id}": {
      "get": {
        "tags": [
          "Product"
        ],
        "parameters": [
          {
            "name": "id",
            "in": "path",
            "required": true,
            "schema": {
              "type": "integer",
              "format": "int32"
            }
          }
        ],
        "responses": {
          "200": {
            "description": "OK",
            "content": {
              "text/plain": {
                "schema": {
                  "type": "array",
                  "items": {
                    "$ref": "#/components/schemas/ProductBr"
                  }
                }
              },
              "application/json": {
                "schema": {
                  "type": "array",
                  "items": {
                    "$ref": "#/components/schemas/ProductBr"
                  }
                }
              },
              "text/json": {
                "schema": {
                  "type": "array",
                  "items": {
                    "$ref": "#/components/schemas/ProductBr"
                  }
                }
              }
            }
          }
        }
      }
    },
    "/api/Product/Getproductbyname{Name}": {
      "get": {
        "tags": [
          "Product"
        ],
        "parameters": [
          {
            "name": "Name",
            "in": "path",
            "required": true,
            "schema": {
              "type": "string"
            }
          }
        ],
        "responses": {
          "200": {
            "description": "OK",
            "content": {
              "text/plain": {
                "schema": {
                  "type": "array",
                  "items": {
                    "$ref": "#/components/schemas/ProductBr"
                  }
                }
              },
              "application/json": {
                "schema": {
                  "type": "array",
                  "items": {
                    "$ref": "#/components/schemas/ProductBr"
                  }
                }
              },
              "text/json": {
                "schema": {
                  "type": "array",
                  "items": {
                    "$ref": "#/components/schemas/ProductBr"
                  }
                }
              }
            }
          }
        }
      }
    },
    "/api/Product/GetImageProduct/{id}": {
      "get": {
        "tags": [
          "Product"
        ],
        "parameters": [
          {
            "name": "id",
            "in": "path",
            "required": true,
            "schema": {
              "type": "integer",
              "format": "int32"
            }
          }
        ],
        "responses": {
          "200": {
            "description": "OK"
          }
        }
      }
    },
    "/api/Product/addProduct": {
      "post": {
        "tags": [
          "Product"
        ],
        "requestBody": {
          "content": {
            "multipart/form-data": {
              "schema": {
                "type": "object",
                "properties": {
                  "Name": {
                    "type": "string"
                  },
                  "price": {
                    "type": "number",
                    "format": "double"
                  },
                  "Description": {
                    "type": "string"
                  },
                  "ImageURL": {
                    "type": "string",
                    "format": "binary"
                  },
                  "CategoryId": {
                    "type": "integer",
                    "format": "int32"
                  },
                  "CategoryName": {
                    "type": "string"
                  }
                }
              },
              "encoding": {
                "Name": {
                  "style": "form"
                },
                "price": {
                  "style": "form"
                },
                "Description": {
                  "style": "form"
                },
                "ImageURL": {
                  "style": "form"
                },
                "CategoryId": {
                  "style": "form"
                },
                "CategoryName": {
                  "style": "form"
                }
              }
            }
          }
        },
        "responses": {
          "200": {
            "description": "OK"
          }
        }
      }
    },
    "/api/Product/DeleteProductbyId{id}": {
      "delete": {
        "tags": [
          "Product"
        ],
        "parameters": [
          {
            "name": "id",
            "in": "path",
            "required": true,
            "schema": {
              "type": "integer",
              "format": "int32"
            }
          }
        ],
        "responses": {
          "200": {
            "description": "OK"
          }
        }
      }
    },
    "/api/Product/GetProductsSortedByPrice": {
      "get": {
        "tags": [
          "Product"
        ],
        "parameters": [
          {
            "name": "sortOrder",
            "in": "query",
            "schema": {
              "type": "string",
              "default": "asc"
            }
          }
        ],
        "responses": {
          "200": {
            "description": "OK"
          }
        }
      }
    },
    "/api/Product/GetProductsSortedByTitleandPrice": {
      "get": {
        "tags": [
          "Product"
        ],
        "parameters": [
          {
            "name": "name",
            "in": "query",
            "schema": {
              "type": "string"
            }
          },
          {
            "name": "sortOrder",
            "in": "query",
            "schema": {
              "type": "string",
              "default": "asc"
            }
          }
        ],
        "responses": {
          "200": {
            "description": "OK"
          }
        }
      }
    },
    "/api/Product/GetProductsSortedByCategoryIdandPrice": {
      "get": {
        "tags": [
          "Product"
        ],
        "parameters": [
          {
            "name": "CategoryId",
            "in": "query",
            "schema": {
              "type": "integer",
              "format": "int32"
            }
          },
          {
            "name": "sortOrder",
            "in": "query",
            "schema": {
              "type": "string",
              "default": "asc"
            }
          }
        ],
        "responses": {
          "200": {
            "description": "OK"
          }
        }
      }
    },
    "/api/Product/GetProductsSortedByCategoryIdandPriceandName": {
      "get": {
        "tags": [
          "Product"
        ],
        "parameters": [
          {
            "name": "name",
            "in": "query",
            "schema": {
              "type": "string"
            }
          },
          {
            "name": "CategoryId",
            "in": "query",
            "schema": {
              "type": "integer",
              "format": "int32"
            }
          },
          {
            "name": "sortOrder",
            "in": "query",
            "schema": {
              "type": "string",
              "default": "asc"
            }
          }
        ],
        "responses": {
          "200": {
            "description": "OK"
          }
        }
      }
    },
    "/api/Users": {
      "get": {
        "tags": [
          "Users"
        ],
        "responses": {
          "200": {
            "description": "OK",
            "content": {
              "text/plain": {
                "schema": {
                  "type": "array",
                  "items": {
                    "$ref": "#/components/schemas/Users"
                  }
                }
              },
              "application/json": {
                "schema": {
                  "type": "array",
                  "items": {
                    "$ref": "#/components/schemas/Users"
                  }
                }
              },
              "text/json": {
                "schema": {
                  "type": "array",
                  "items": {
                    "$ref": "#/components/schemas/Users"
                  }
                }
              }
            }
          }
        }
      }
    },
    "/api/Users/{id}": {
      "get": {
        "tags": [
          "Users"
        ],
        "parameters": [
          {
            "name": "id",
            "in": "path",
            "required": true,
            "schema": {
              "type": "integer",
              "format": "int32"
            }
          }
        ],
        "responses": {
          "200": {
            "description": "OK",
            "content": {
              "text/plain": {
                "schema": {
                  "$ref": "#/components/schemas/Users"
                }
              },
              "application/json": {
                "schema": {
                  "$ref": "#/components/schemas/Users"
                }
              },
              "text/json": {
                "schema": {
                  "$ref": "#/components/schemas/Users"
                }
              }
            }
          }
        }
      }
    }
  },
  "components": {
    "schemas": {
      "CardInfo": {
        "type": "object",
        "properties": {
          "cardHolderName": {
            "type": "string",
            "nullable": true
          },
          "cardNumber": {
            "type": "string",
            "nullable": true
          },
          "expirationDate": {
            "type": "string",
            "nullable": true
          },
          "cvv": {
            "type": "string",
            "nullable": true
          }
        },
        "additionalProperties": false
      },
      "ChangePasswordDto": {
        "type": "object",
        "properties": {
          "email": {
            "type": "string",
            "nullable": true
          },
          "oldPassword": {
            "type": "string",
            "nullable": true
          },
          "newPassword": {
            "type": "string",
            "nullable": true
          }
        },
        "additionalProperties": false
      },
      "CheckoutForm": {
        "type": "object",
        "properties": {
          "id": {
            "type": "integer",
            "format": "int32"
          },
          "fullName": {
            "type": "string",
            "nullable": true
          },
          "phoneNumber": {
            "type": "string",
            "nullable": true
          },
          "email": {
            "type": "string",
            "nullable": true
          },
          "country": {
            "type": "string",
            "nullable": true
          },
          "state": {
            "type": "string",
            "nullable": true
          },
          "city": {
            "type": "string",
            "nullable": true
          },
          "address1": {
            "type": "string",
            "nullable": true
          },
          "address2": {
            "type": "string",
            "nullable": true
          },
          "postalCode": {
            "type": "string",
            "nullable": true
          },
          "notes": {
            "type": "string",
            "nullable": true
          },
          "paymentMethod": {
            "type": "string",
            "nullable": true
          },
          "orderId": {
            "type": "integer",
            "format": "int32"
          },
          "cardInfo": {
            "$ref": "#/components/schemas/CardInfo"
          }
        },
        "additionalProperties": false
      },
      "OrderDetailDto": {
        "type": "object",
        "properties": {
          "productId": {
            "type": "integer",
            "format": "int32"
          },
          "quantity": {
            "type": "integer",
            "format": "int32"
          },
          "unitPrice": {
            "type": "number",
            "format": "double"
          }
        },
        "additionalProperties": false
      },
      "OrderDto": {
        "type": "object",
        "properties": {
          "id": {
            "type": "integer",
            "format": "int32"
          },
          "orderDate": {
            "type": "string",
            "format": "date-time"
          },
          "customerId": {
            "type": "string",
            "nullable": true
          },
          "orderDetails": {
            "type": "array",
            "items": {
              "$ref": "#/components/schemas/OrderDetailDto"
            },
            "nullable": true
          }
        },
        "additionalProperties": false
      },
      "ProductBr": {
        "type": "object",
        "properties": {
          "id": {
            "type": "integer",
            "format": "int32"
          },
          "name": {
            "type": "string",
            "nullable": true
          },
          "price": {
            "type": "number",
            "format": "double"
          },
          "description": {
            "type": "string",
            "nullable": true
          },
          "categoryId": {
            "type": "integer",
            "format": "int32"
          },
          "categoryName": {
            "type": "string",
            "nullable": true,
            "readOnly": true
          }
        },
        "additionalProperties": false
      },
      "ProductDto": {
        "type": "object",
        "properties": {
          "name": {
            "type": "string",
            "nullable": true
          },
          "price": {
            "type": "number",
            "format": "double"
          },
          "description": {
            "type": "string",
            "nullable": true
          },
          "imageURL": {
            "type": "string",
            "format": "binary",
            "nullable": true
          },
          "categoryId": {
            "type": "integer",
            "format": "int32"
          },
          "categoryName": {
            "type": "string",
            "nullable": true,
            "readOnly": true
          }
        },
        "additionalProperties": false
      },
      "UserLogin": {
        "type": "object",
        "properties": {
          "email": {
            "type": "string",
            "nullable": true
          },
          "password": {
            "type": "string",
            "nullable": true
          }
        },
        "additionalProperties": false
      },
      "UserSignUp": {
        "type": "object",
        "properties": {
          "firstName": {
            "type": "string",
            "nullable": true
          },
          "lastName": {
            "type": "string",
            "nullable": true
          },
          "email": {
            "type": "string",
            "nullable": true
          },
          "gender": {
            "type": "string",
            "nullable": true
          },
          "password": {
            "type": "string",
            "nullable": true
          },
          "passwordConfirm": {
            "type": "string",
            "nullable": true
          }
        },
        "additionalProperties": false
      },
      "Users": {
        "type": "object",
        "properties": {
          "userId": {
            "type": "integer",
            "format": "int32"
          },
          "firstName": {
            "type": "string",
            "nullable": true
          },
          "lastName": {
            "type": "string",
            "nullable": true
          },
          "email": {
            "type": "string",
            "nullable": true
          },
          "gender": {
            "type": "string",
            "nullable": true
          },
          "passwordSalt": {
            "type": "string",
            "format": "byte",
            "nullable": true
          },
          "passwordHash": {
            "type": "string",
            "format": "byte",
            "nullable": true
          }
        },
        "additionalProperties": false
      },
      "ViewOrder": {
        "type": "object",
        "properties": {
          "checkoutFormId": {
            "type": "integer",
            "format": "int32"
          },
          "orderId": {
            "type": "integer",
            "format": "int32"
          },
          "orderDto": {
            "$ref": "#/components/schemas/OrderDto"
          },
          "customerName": {
            "type": "string",
            "nullable": true
          },
          "customerEmail": {
            "type": "string",
            "nullable": true
          },
          "customerPhone": {
            "type": "string",
            "nullable": true
          },
          "customerLocation": {
            "type": "string",
            "nullable": true
          },
          "price": {
            "type": "integer",
            "format": "int32",
            "nullable": true
          },
          "paymentMethod": {
            "type": "string",
            "nullable": true
          }
        },
        "additionalProperties": false
      }
    }
  }
}